{
  "aadvarq": [
    {
      "count": 3097,
      "date": "2026-06-29"
    }
  ],
  "alfredo": [
    {
      "count": 4238,
      "date": "2026-06-29"
    }
  ],
  "almanac": [
    {
      "count": 4215,
      "date": "2026-06-29"
    }
  ],
  "convert": [
    {
      "count": 5163,
      "date": "2026-06-29"
    }
  ],
  "fakeum": [
    {
      "count": 4359,
      "date": "2026-06-29"
    }
  ],
  "leasechecker": [
    {
      "count": 2423,
      "date": "2026-06-29"
    }
  ],
  "michelin-guide": [
    {
      "count": 951,
      "date": "2026-06-29"
    }
  ],
  "outlook-suite": [
    {
      "count": 4398,
      "date": "2026-06-29"
    }
  ],
  "phonetic-spelling": [
    {
      "count": 2777,
      "date": "2026-06-29"
    }
  ],
  "quickcensus": [
    {
      "count": 2907,
      "date": "2026-06-29"
    }
  ],
  "readwise": [
    {
      "count": 2721,
      "date": "2026-06-29"
    }
  ],
  "searchio": [
    {
      "count": 796,
      "date": "2026-06-29"
    }
  ],
  "whowaswhen": [
    {
      "count": 1148,
      "date": "2026-06-29"
    }
  ],
  "xkcd": [
    {
      "count": 1194,
      "date": "2026-06-29"
    }
  ],
  "zothero": [
    {
      "count": 3809,
      "date": "2026-06-29"
    }
  ]
}
